email2slack/__init__.py
email2slack/__main__.py
email2slack/compat.py
email2slack/parser.py
email2slack/slack.py
email2slack-1.0.0a6.dist-info/LICENSE
email2slack-1.0.0a6.dist-info/METADATA
email2slack-1.0.0a6.dist-info/WHEEL
email2slack-1.0.0a6.dist-info/entry_points.txt
email2slack-1.0.0a6.dist-info/top_level.txt
email2slack-1.0.0a6.dist-info/RECORD
