Metadata-Version: 2.1
Name: email2slack
Version: 1.0.0a6
Summary: MIME E-mail forwarding script for Slack written in Python
Home-page: https://github.com/mikoim/email2slack
Author: Eshin Kunishima
Author-email: ek@esh.ink
License: MIT
Keywords: email slack forwarding
Platform: UNKNOWN
Classifier: Development Status :: 3 - Alpha
Classifier: Topic :: Communications
Classifier: Topic :: Communications :: Email
Classifier: Topic :: Communications :: Email :: Mail Transport Agents
Classifier: Topic :: Communications :: Chat
Classifier: License :: OSI Approved :: MIT License
Classifier: Programming Language :: Python
Classifier: Programming Language :: Python :: 2
Classifier: Programming Language :: Python :: 2.7
Classifier: Programming Language :: Python :: 3
Classifier: Programming Language :: Python :: 3.4
Classifier: Programming Language :: Python :: 3.5
Classifier: Programming Language :: Python :: 3.6
Classifier: Programming Language :: Python :: 3.7
Requires-Dist: beautifulsoup4 (<5,>=4.6.0)
Requires-Dist: requests (<3,>=2.18.2)
Requires-Dist: html5lib (==1.0.1)
Provides-Extra: lxml
Requires-Dist: lxml (<4.4.0,>=4.1.1) ; extra == 'lxml'
Provides-Extra: nkf
Requires-Dist: nkf (==0.2.0) ; extra == 'nkf'
Provides-Extra: test
Requires-Dist: pytest ; extra == 'test'
